BubotObj/OcfDevice/OcfDevice.md
BubotObj/OcfDevice/OcfDevice.py
BubotObj/OcfDevice/OcfDeviceApi.py
BubotObj/OcfDevice/forms/FoundDevices.form.json
BubotObj/OcfDevice/forms/Item.form.json
BubotObj/OcfDevice/forms/List.form.json
BubotObj/OcfDevice/subtype/AdminPanel/AdminPanel.json
BubotObj/OcfDevice/subtype/AdminPanel/AdminPanel.py
BubotObj/OcfDevice/subtype/AdminPanel/AdminPanelApi.py
BubotObj/OcfDevice/subtype/AdminPanel/__init__.py
BubotObj/OcfDevice/subtype/AdminPanel/i18n/cn.json
BubotObj/OcfDevice/subtype/AdminPanel/i18n/en.json
BubotObj/OcfDevice/subtype/AdminPanel/i18n/ru.json
BubotObj/OcfDevice/subtype/AdminPanel/static/ui/index.html
BubotObj/OcfDevice/subtype/AdminPanel/static/ui/css/chunk-03738786.875a899d.css
BubotObj/OcfDevice/subtype/AdminPanel/static/ui/css/chunk-07626ab0.7bf428e5.css
BubotObj/OcfDevice/subtype/AdminPanel/static/ui/css/chunk-0c37d0ac.4c6fc861.css
BubotObj/OcfDevice/subtype/AdminPanel/static/ui/css/chunk-110ca456.d1c7f804.css
BubotObj/OcfDevice/subtype/AdminPanel/static/ui/css/chunk-12815540.7bf428e5.css
BubotObj/OcfDevice/subtype/AdminPanel/static/ui/css/chunk-194d1552.a76b608a.css
BubotObj/OcfDevice/subtype/AdminPanel/static/ui/css/chunk-244692cf.0e433876.css
BubotObj/OcfDevice/subtype/AdminPanel/static/ui/css/chunk-256b0cb7.85e964b6.css
BubotObj/OcfDevice/subtype/AdminPanel/static/ui/css/chunk-26119db4.d5303573.css
BubotObj/OcfDevice/subtype/AdminPanel/static/ui/css/chunk-2aacef1c.200e19c2.css
BubotObj/OcfDevice/subtype/AdminPanel/static/ui/css/chunk-2bbc5a94.a5721ec9.css
BubotObj/OcfDevice/subtype/AdminPanel/static/ui/css/chunk-2c33c399.3e56c8e1.css
BubotObj/OcfDevice/subtype/AdminPanel/static/ui/css/chunk-2e05b644.c07c4b9a.css
BubotObj/OcfDevice/subtype/AdminPanel/static/ui/css/chunk-31571dd7.533c4710.css
BubotObj/OcfDevice/subtype/AdminPanel/static/ui/css/chunk-35c10bce.1b360f64.css
BubotObj/OcfDevice/subtype/AdminPanel/static/ui/css/chunk-3633e4e3.66ff4bbb.css
Bubot_AdminPanel-0.0.2.dist-info/LICENSE
Bubot_AdminPanel-0.0.2.dist-info/METADATA
Bubot_AdminPanel-0.0.2.dist-info/WHEEL
Bubot_AdminPanel-0.0.2.dist-info/top_level.txt
Bubot_AdminPanel-0.0.2.dist-info/RECORD
