Metadata-Version: 2.1
Name: Bubot-AdminPanel
Version: 0.0.2
Summary: Admin web interface for smart home based on OCF standard.
Home-page: https://github.com/businka/Bubot_AdminPanel
Author: Razgovorov Mikhail
Author-email: 1338833@gmail.com
License: UNKNOWN
Platform: UNKNOWN
Classifier: Programming Language :: Python :: 3
Classifier: License :: OSI Approved :: MIT License
Classifier: Operating System :: OS Independent
Classifier: Development Status :: 3 - Alpha
Classifier: Framework :: AsyncIO
Requires-Python: >=3.7
Requires-Dist: Bubot-WebServer
